LordNzb/__init__.py
LordNzb/cli.py
LordNzb/core/__init__.py
LordNzb/core/descriptor.py
LordNzb/core/reg.py
LordNzb-2024.3.1.1.dist-info/METADATA
LordNzb-2024.3.1.1.dist-info/WHEEL
LordNzb-2024.3.1.1.dist-info/entry_points.txt
LordNzb-2024.3.1.1.dist-info/top_level.txt
LordNzb-2024.3.1.1.dist-info/RECORD
