Metadata-Version: 2.1
Name: LordNzb
Version: 2024.3.1.1
Summary: Nzb parser Lib für python
Author-email: lordbex <lordibex@protonmail.com>
Maintainer-email: lordbex <lordibex@protonmail.com>
Project-URL: homepage, https://github.com/BexWorld/LordNzb
Project-URL: repository, https://github.com/BexWorld/LordNzb
Classifier: Operating System :: OS Independent
Classifier: Programming Language :: Python
Classifier: Programming Language :: Python :: 3.10
Classifier: Topic :: Software Development :: Libraries :: Python Modules
Requires-Python: >=3.10
Requires-Dist: regex
